mcrn/__init__.py
mcrn-0.0.1.dist-info/METADATA
mcrn-0.0.1.dist-info/RECORD
mcrn-0.0.1.dist-info/WHEEL
mcrn-0.0.1.dist-info/top_level.txt
