Metadata-Version: 2.1
Name: mcrn
Version: 0.0.1
Summary: Configuration management framework for small networks.
Home-page: https://github.com/aequitas/mcrn
Author: Johan Bloemberg
Author-email: mcrn@ijohan.nl
License: UNKNOWN
Platform: UNKNOWN
Classifier: Programming Language :: Python :: 3
Classifier: License :: OSI Approved :: MIT License
Classifier: Operating System :: OS Independent
